{
  "K02C": {
    "Id": "K02C",
    "Name": "CAPITOL",
    "Latitude": 43.089617,
    "Longitude": -88.179439,
    "Url": "https://www.airportiq5010.com/5010ReportRouter/default.aspx?airportID=02C",
    "Distance": 0
  },
  "K11Y": {
    "Id": "K11Y",
    "Name": "FLYING FEATHERS",
    "Latitude": 44.061183,
    "Longitude": -88.194933,
    "Url": "https://www.airportiq5010.com/5010ReportRouter/default.aspx?airportID=11Y",
    "Distance": 0
  },
  "K1H9": {
    "Id": "K1H9",
    "Name": "NEST OF EAGLES",
    "Latitude": 45.835614,
    "Longitude": -91.802836,
    "Url": "https://www.airportiq5010.com/5010ReportRouter/default.aspx?airportID=1H9",
    "Distance": 0
  },
  "K2P2": {
    "Id": "K2P2",
    "Name": "WASHINGTON ISLAND",
    "Latitude": 45.388253,
    "Longitude": -86.924039,
    "Url": "https://www.airportiq5010.com/5010ReportRouter/default.aspx?airportID=2P2",
    "Distance": 0
  },
  "K3CU": {
    "Id": "K3CU",
    "Name": "CABLE UNION",
    "Latitude": 46.194931,
    "Longitude": -91.248453,
    "Url": "https://www.airportiq5010.com/5010ReportRouter/default.aspx?airportID=3CU",
    "Distance": 0
  },
  "K3D1": {
    "Id": "K3D1",
    "Name": "CRIVITZ MUNI",
    "Latitude": 45.214639,
    "Longitude": -88.073297,
    "Url": "https://www.airportiq5010.com/5010ReportRouter/default.aspx?airportID=3D1",
    "Distance": 0
  },
  "K3D2": {
    "Id": "K3D2",
    "Name": "EPHRAIM-GIBRALTAR",
    "Latitude": 45.135706,
    "Longitude": -87.188128,
    "Url": "https://www.airportiq5010.com/5010ReportRouter/default.aspx?airportID=3D2",
    "Distance": 0
  },
  "K3T3": {
    "Id": "K3T3",
    "Name": "BOYCEVILLE MUNI",
    "Latitude": 45.043953,
    "Longitude": -92.021328,
    "Url": "https://www.airportiq5010.com/5010ReportRouter/default.aspx?airportID=3T3",
    "Distance": 0
  },
  "K40D": {
    "Id": "K40D",
    "Name": "THREE LAKES MUNI",
    "Latitude": 45.790233,
    "Longitude": -89.120958,
    "Url": "https://www.airportiq5010.com/5010ReportRouter/default.aspx?airportID=40D",
    "Distance": 0
  },
  "K44C": {
    "Id": "K44C",
    "Name": "BELOIT",
    "Latitude": 42.497778,
    "Longitude": -88.967611,
    "Url": "https://www.airportiq5010.com/5010ReportRouter/default.aspx?airportID=44C",
    "Distance": 0
  },
  "K49C": {
    "Id": "K49C",
    "Name": "CAMP LAKE",
    "Latitude": 42.53335,
    "Longitude": -88.158419,
    "Url": "https://www.airportiq5010.com/5010ReportRouter/default.aspx?airportID=49C",
    "Distance": 0
  },
  "K4D1": {
    "Id": "K4D1",
    "Name": "THREE CASTLES",
    "Latitude": 43.669972,
    "Longitude": -90.232628,
    "Url": "https://www.airportiq5010.com/5010ReportRouter/default.aspx?airportID=4D1",
    "Distance": 0
  },
  "K4R5": {
    "Id": "K4R5",
    "Name": "MAJOR GILBERT",
    "Latitude": 46.788667,
    "Longitude": -90.758722,
    "Url": "https://www.airportiq5010.com/5010ReportRouter/default.aspx?airportID=4R5",
    "Distance": 0
  },
  "K54W": {
    "Id": "K54W",
    "Name": "ALBANY",
    "Latitude": 42.717386,
    "Longitude": -89.424183,
    "Url": "https://www.airportiq5010.com/5010ReportRouter/default.aspx?airportID=54W",
    "Distance": 0
  },
  "K57C": {
    "Id": "K57C",
    "Name": "EAST TROY MUNI",
    "Latitude": 42.797167,
    "Longitude": -88.372611,
    "Url": "https://www.airportiq5010.com/5010ReportRouter/default.aspx?airportID=57C",
    "Distance": 0
  },
  "K58C": {
    "Id": "K58C",
    "Name": "JANA",
    "Latitude": 42.872781,
    "Longitude": -89.075667,
    "Url": "https://www.airportiq5010.com/5010ReportRouter/default.aspx?airportID=58C",
    "Distance": 0
  },
  "K5G4": {
    "Id": "K5G4",
    "Name": "EAU CLAIRE LAKES",
    "Latitude": 46.348389,
    "Longitude": -91.4965,
    "Url": "https://www.airportiq5010.com/5010ReportRouter/default.aspx?airportID=5G4",
    "Distance": 0
  },
  "K5N2": {
    "Id": "K5N2",
    "Name": "PRENTICE",
    "Latitude": 45.538331,
    "Longitude": -90.276333,
    "Url": "https://www.airportiq5010.com/5010ReportRouter/default.aspx?airportID=5N2",
    "Distance": 0
  },
  "K5Y3": {
    "Id": "K5Y3",
    "Name": "GUTZMERS TWIN",
    "Latitude": 42.853556,
    "Longitude": -88.759806,
    "Url": "https://www.airportiq5010.com/5010ReportRouter/default.aspx?airportID=5Y3",
    "Distance": 0
  },
  "K60C": {
    "Id": "K60C",
    "Name": "ELROY MUNI",
    "Latitude": 43.706361,
    "Longitude": -90.257628,
    "Url": "https://www.airportiq5010.com/5010ReportRouter/default.aspx?airportID=60C",
    "Distance": 0
  },
  "K61C": {
    "Id": "K61C",
    "Name": "FORT ATKINSON MUNI",
    "Latitude": 42.963203,
    "Longitude": -88.817628,
    "Url": "https://www.airportiq5010.com/5010ReportRouter/default.aspx?airportID=61C",
    "Distance": 0
  },
  "K62C": {
    "Id": "K62C",
    "Name": "CINDY GUNTLY",
    "Latitude": 42.810939,
    "Longitude": -88.094036,
    "Url": "https://www.airportiq5010.com/5010ReportRouter/default.aspx?airportID=62C",
    "Distance": 0
  },
  "K63C": {
    "Id": "K63C",
    "Name": "ADAMS COUNTY",
    "Latitude": 43.960586,
    "Longitude": -89.788644,
    "Url": "https://www.airportiq5010.com/5010ReportRouter/default.aspx?airportID=63C",
    "Distance": 0
  },
  "K68C": {
    "Id": "K68C",
    "Name": "CENTRAL COUNTY",
    "Latitude": 44.505536,
    "Longitude": -89.025108,
    "Url": "https://www.airportiq5010.com/5010ReportRouter/default.aspx?airportID=68C",
    "Distance": 0
  },
  "K6P3": {
    "Id": "K6P3",
    "Name": "WAUNAKEE",
    "Latitude": 43.178722,
    "Longitude": -89.451278,
    "Url": "https://www.airportiq5010.com/5010ReportRouter/default.aspx?airportID=6P3",
    "Distance": 0
  },
  "K73C": {
    "Id": "K73C",
    "Name": "LANCASTER MUNI",
    "Latitude": 42.782528,
    "Longitude": -90.681083,
    "Url": "https://www.airportiq5010.com/5010ReportRouter/default.aspx?airportID=73C",
    "Distance": 0
  },
  "K79C": {
    "Id": "K79C",
    "Name": "BRENNAND",
    "Latitude": 44.159983,
    "Longitude": -88.559553,
    "Url": "https://www.airportiq5010.com/5010ReportRouter/default.aspx?airportID=79C",
    "Distance": 0
  },
  "K7P5": {
    "Id": "K7P5",
    "Name": "PISO",
    "Latitude": 45.065417,
    "Longitude": -88.427083,
    "Url": "https://www.airportiq5010.com/5010ReportRouter/default.aspx?airportID=7P5",
    "Distance": 0
  },
  "K7V3": {
    "Id": "K7V3",
    "Name": "BIG FOOT AIRFIELD",
    "Latitude": 42.527419,
    "Longitude": -88.651392,
    "Url": "https://www.airportiq5010.com/5010ReportRouter/default.aspx?airportID=7V3",
    "Distance": 0
  },
  "K82C": {
    "Id": "K82C",
    "Name": "MAUSTON-NEW LISBON",
    "Latitude": 43.838767,
    "Longitude": -90.137733,
    "Url": "https://www.airportiq5010.com/5010ReportRouter/default.aspx?airportID=82C",
    "Distance": 0
  },
  "K87Y": {
    "Id": "K87Y",
    "Name": "BLACKHAWK AIRFIELD",
    "Latitude": 43.104703,
    "Longitude": -89.185361,
    "Url": "https://www.airportiq5010.com/5010ReportRouter/default.aspx?airportID=87Y",
    "Distance": 0
  },
  "K88C": {
    "Id": "K88C",
    "Name": "PALMYRA MUNI",
    "Latitude": 42.883544,
    "Longitude": -88.599917,
    "Url": "https://www.airportiq5010.com/5010ReportRouter/default.aspx?airportID=88C",
    "Distance": 0
  },
  "K8D1": {
    "Id": "K8D1",
    "Name": "NEW HOLSTEIN MUNI",
    "Latitude": 43.944103,
    "Longitude": -88.114842,
    "Url": "https://www.airportiq5010.com/5010ReportRouter/default.aspx?airportID=8D1",
    "Distance": 0
  },
  "K91C": {
    "Id": "K91C",
    "Name": "SAUK-PRAIRIE",
    "Latitude": 43.297861,
    "Longitude": -89.755806,
    "Url": "https://www.airportiq5010.com/5010ReportRouter/default.aspx?airportID=91C",
    "Distance": 0
  },
  "K92C": {
    "Id": "K92C",
    "Name": "CARTER",
    "Latitude": 44.641017,
    "Longitude": -88.214519,
    "Url": "https://www.airportiq5010.com/5010ReportRouter/default.aspx?airportID=92C",
    "Distance": 0
  },
  "K93C": {
    "Id": "K93C",
    "Name": "RICHLAND",
    "Latitude": 43.283356,
    "Longitude": -90.298281,
    "Url": "https://www.airportiq5010.com/5010ReportRouter/default.aspx?airportID=93C",
    "Distance": 0
  },
  "K94C": {
    "Id": "K94C",
    "Name": "GILBERT FIELD",
    "Latitude": 43.449983,
    "Longitude": -89.250114,
    "Url": "https://www.airportiq5010.com/5010ReportRouter/default.aspx?airportID=94C",
    "Distance": 0
  },
  "K96C": {
    "Id": "K96C",
    "Name": "FOX RIVER",
    "Latitude": 42.750014,
    "Longitude": -88.250922,
    "Url": "https://www.airportiq5010.com/5010ReportRouter/default.aspx?airportID=96C",
    "Distance": 0
  },
  "K9Y7": {
    "Id": "K9Y7",
    "Name": "BARRON MUNI",
    "Latitude": 45.407456,
    "Longitude": -91.834339,
    "Url": "https://www.airportiq5010.com/5010ReportRouter/default.aspx?airportID=9Y7",
    "Distance": 0
  },
  "KAHH": {
    "Id": "KAHH",
    "Name": "AMERY MUNI",
    "Latitude": 45.281147,
    "Longitude": -92.375392,
    "Url": "https://www.airportiq5010.com/5010ReportRouter/default.aspx?airportID=AHH",
    "Distance": 0
  },
  "KAIG": {
    "Id": "KAIG",
    "Name": "LANGLADE COUNTY",
    "Latitude": 45.153947,
    "Longitude": -89.110617,
    "Url": "https://www.airportiq5010.com/5010ReportRouter/default.aspx?airportID=AIG",
    "Distance": 0
  },
  "KARV": {
    "Id": "KARV",
    "Name": "LAKELAND/NOBLE F",
    "Latitude": 45.927917,
    "Longitude": -89.730944,
    "Url": "https://www.airportiq5010.com/5010ReportRouter/default.aspx?airportID=ARV",
    "Distance": 0
  },
  "KASX": {
    "Id": "KASX",
    "Name": "JOHN F KENNEDY",
    "Latitude": 46.548528,
    "Longitude": -90.918972,
    "Url": "https://www.airportiq5010.com/5010ReportRouter/default.aspx?airportID=ASX",
    "Distance": 0
  },
  "KATW": {
    "Id": "KATW",
    "Name": "APPLETON INTL",
    "Latitude": 44.258083,
    "Longitude": -88.519083,
    "Url": "https://www.airportiq5010.com/5010ReportRouter/default.aspx?airportID=ATW",
    "Distance": 0
  },
  "KAUW": {
    "Id": "KAUW",
    "Name": "WAUSAU DOWNTOWN",
    "Latitude": 44.926283,
    "Longitude": -89.627,
    "Url": "https://www.airportiq5010.com/5010ReportRouter/default.aspx?airportID=AUW",
    "Distance": 0
  },
  "KBCK": {
    "Id": "KBCK",
    "Name": "BLACK RIVER FALLS",
    "Latitude": 44.250736,
    "Longitude": -90.855278,
    "Url": "https://www.airportiq5010.com/5010ReportRouter/default.aspx?airportID=BCK",
    "Distance": 0
  },
  "KBDJ": {
    "Id": "KBDJ",
    "Name": "BOULDER JUNCTION",
    "Latitude": 46.137447,
    "Longitude": -89.645983,
    "Url": "https://www.airportiq5010.com/5010ReportRouter/default.aspx?airportID=BDJ",
    "Distance": 0
  },
  "KBUU": {
    "Id": "KBUU",
    "Name": "BURLINGTON MUNI",
    "Latitude": 42.690717,
    "Longitude": -88.304681,
    "Url": "https://www.airportiq5010.com/5010ReportRouter/default.aspx?airportID=BUU",
    "Distance": 0
  },
  "KC02": {
    "Id": "KC02",
    "Name": "GRAND GENEVA",
    "Latitude": 42.614917,
    "Longitude": -88.389583,
    "Url": "https://www.airportiq5010.com/5010ReportRouter/default.aspx?airportID=C02",
    "Distance": 0
  },
  "KC29": {
    "Id": "KC29",
    "Name": "MIDDLETON MUNI -",
    "Latitude": 43.114328,
    "Longitude": -89.531647,
    "Url": "https://www.airportiq5010.com/5010ReportRouter/default.aspx?airportID=C29",
    "Distance": 0
  },
  "KC35": {
    "Id": "KC35",
    "Name": "REEDSBURG MUNI",
    "Latitude": 43.525897,
    "Longitude": -89.983219,
    "Url": "https://www.airportiq5010.com/5010ReportRouter/default.aspx?airportID=C35",
    "Distance": 0
  },
  "KC37": {
    "Id": "KC37",
    "Name": "BRODHEAD",
    "Latitude": 42.595997,
    "Longitude": -89.381697,
    "Url": "https://www.airportiq5010.com/5010ReportRouter/default.aspx?airportID=C37",
    "Distance": 0
  },
  "KC47": {
    "Id": "KC47",
    "Name": "PORTAGE MUNI",
    "Latitude": 43.560306,
    "Longitude": -89.482861,
    "Url": "https://www.airportiq5010.com/5010ReportRouter/default.aspx?airportID=C47",
    "Distance": 0
  },
  "KC59": {
    "Id": "KC59",
    "Name": "LAKE LAWN",
    "Latitude": 42.634125,
    "Longitude": -88.601128,
    "Url": "https://www.airportiq5010.com/5010ReportRouter/default.aspx?airportID=C59",
    "Distance": 0
  },
  "KC74": {
    "Id": "KC74",
    "Name": "CASSVILLE MUNI",
    "Latitude": 42.704269,
    "Longitude": -90.966106,
    "Url": "https://www.airportiq5010.com/5010ReportRouter/default.aspx?airportID=C74",
    "Distance": 0
  },
  "KC89": {
    "Id": "KC89",
    "Name": "SYLVANIA",
    "Latitude": 42.70325,
    "Longitude": -87.958972,
    "Url": "https://www.airportiq5010.com/5010ReportRouter/default.aspx?airportID=C89",
    "Distance": 0
  },
  "KCLI": {
    "Id": "KCLI",
    "Name": "CLINTONVILLE MUNI",
    "Latitude": 44.613167,
    "Longitude": -88.730889,
    "Url": "https://www.airportiq5010.com/5010ReportRouter/default.aspx?airportID=CLI",
    "Distance": 0
  },
  "KCMY": {
    "Id": "KCMY",
    "Name": "SPARTA/FORT MC COY",
    "Latitude": 43.958292,
    "Longitude": -90.737933,
    "Url": "https://www.airportiq5010.com/5010ReportRouter/default.aspx?airportID=CMY",
    "Distance": 0
  },
  "KCWA": {
    "Id": "KCWA",
    "Name": "CENTRAL WISCONSIN",
    "Latitude": 44.777622,
    "Longitude": -89.666778,
    "Url": "https://www.airportiq5010.com/5010ReportRouter/default.aspx?airportID=CWA",
    "Distance": 0
  },
  "KD25": {
    "Id": "KD25",
    "Name": "MANITOWISH WATERS",
    "Latitude": 46.120225,
    "Longitude": -89.882197,
    "Url": "https://www.airportiq5010.com/5010ReportRouter/default.aspx?airportID=D25",
    "Distance": 0
  },
  "KDAF": {
    "Id": "KDAF",
    "Name": "NECEDAH",
    "Latitude": 44.033444,
    "Longitude": -90.085111,
    "Url": "https://www.airportiq5010.com/5010ReportRouter/default.aspx?airportID=DAF",
    "Distance": 0
  },
  "KDLL": {
    "Id": "KDLL",
    "Name": "BARABOO-WISCONSIN",
    "Latitude": 43.522028,
    "Longitude": -89.77125,
    "Url": "https://www.airportiq5010.com/5010ReportRouter/default.aspx?airportID=DLL",
    "Distance": 0
  },
  "KEAU": {
    "Id": "KEAU",
    "Name": "CHIPPEWA VALLEY",
    "Latitude": 44.865806,
    "Longitude": -91.48425,
    "Url": "https://www.airportiq5010.com/5010ReportRouter/default.aspx?airportID=EAU",
    "Distance": 0
  },
  "KEFT": {
    "Id": "KEFT",
    "Name": "MONROE MUNI",
    "Latitude": 42.6149,
    "Longitude": -89.590403,
    "Url": "https://www.airportiq5010.com/5010ReportRouter/default.aspx?airportID=EFT",
    "Distance": 0
  },
  "KEGV": {
    "Id": "KEGV",
    "Name": "EAGLE RIVER UNION",
    "Latitude": 45.932333,
    "Longitude": -89.268278,
    "Url": "https://www.airportiq5010.com/5010ReportRouter/default.aspx?airportID=EGV",
    "Distance": 0
  },
  "KENW": {
    "Id": "KENW",
    "Name": "KENOSHA RGNL",
    "Latitude": 42.595694,
    "Longitude": -87.927806,
    "Url": "https://www.airportiq5010.com/5010ReportRouter/default.aspx?airportID=ENW",
    "Distance": 0
  },
  "KETB": {
    "Id": "KETB",
    "Name": "WEST BEND MUNI",
    "Latitude": 43.422167,
    "Longitude": -88.127917,
    "Url": "https://www.airportiq5010.com/5010ReportRouter/default.aspx?airportID=ETB",
    "Distance": 0
  },
  "KEZS": {
    "Id": "KEZS",
    "Name": "SHAWANO MUNI",
    "Latitude": 44.787306,
    "Longitude": -88.560014,
    "Url": "https://www.airportiq5010.com/5010ReportRouter/default.aspx?airportID=EZS",
    "Distance": 0
  },
  "KFLD": {
    "Id": "KFLD",
    "Name": "FOND DU LAC COUNTY",
    "Latitude": 43.771167,
    "Longitude": -88.488417,
    "Url": "https://www.airportiq5010.com/5010ReportRouter/default.aspx?airportID=FLD",
    "Distance": 0
  },
  "KGRB": {
    "Id": "KGRB",
    "Name": "GREEN BAY-AUSTIN",
    "Latitude": 44.484633,
    "Longitude": -88.129711,
    "Url": "https://www.airportiq5010.com/5010ReportRouter/default.aspx?airportID=GRB",
    "Distance": 0
  },
  "KGTG": {
    "Id": "KGTG",
    "Name": "GRANTSBURG MUNI",
    "Latitude": 45.798378,
    "Longitude": -92.664331,
    "Url": "https://www.airportiq5010.com/5010ReportRouter/default.aspx?airportID=GTG",
    "Distance": 0
  },
  "KHXF": {
    "Id": "KHXF",
    "Name": "HARTFORD MUNI",
    "Latitude": 43.350047,
    "Longitude": -88.390239,
    "Url": "https://www.airportiq5010.com/5010ReportRouter/default.aspx?airportID=HXF",
    "Distance": 0
  },
  "KHYR": {
    "Id": "KHYR",
    "Name": "SAWYER COUNTY",
    "Latitude": 46.025264,
    "Longitude": -91.444264,
    "Url": "https://www.airportiq5010.com/5010ReportRouter/default.aspx?airportID=HYR",
    "Distance": 0
  },
  "KIMT": {
    "Id": "KIMT",
    "Name": "FORD",
    "Latitude": 45.818361,
    "Longitude": -88.114556,
    "Url": "https://www.airportiq5010.com/5010ReportRouter/default.aspx?airportID=IMT",
    "Distance": 0
  },
  "KISW": {
    "Id": "KISW",
    "Name": "ALEXANDER FIELD",
    "Latitude": 44.360353,
    "Longitude": -89.839039,
    "Url": "https://www.airportiq5010.com/5010ReportRouter/default.aspx?airportID=ISW",
    "Distance": 0
  },
  "KIWD": {
    "Id": "KIWD",
    "Name": "GOGEBIC-IRON",
    "Latitude": 46.527472,
    "Longitude": -90.131389,
    "Url": "https://www.airportiq5010.com/5010ReportRouter/default.aspx?airportID=IWD",
    "Distance": 0
  },
  "KJVL": {
    "Id": "KJVL",
    "Name": "SOUTHERN WISCONSIN",
    "Latitude": 42.62025,
    "Longitude": -89.041556,
    "Url": "https://www.airportiq5010.com/5010ReportRouter/default.aspx?airportID=JVL",
    "Distance": 0
  },
  "KLNL": {
    "Id": "KLNL",
    "Name": "KINGS LAND O",
    "Latitude": 46.154117,
    "Longitude": -89.211964,
    "Url": "https://www.airportiq5010.com/5010ReportRouter/default.aspx?airportID=LNL",
    "Distance": 0
  },
  "KLNR": {
    "Id": "KLNR",
    "Name": "TRI-COUNTY RGNL",
    "Latitude": 43.211861,
    "Longitude": -90.179833,
    "Url": "https://www.airportiq5010.com/5010ReportRouter/default.aspx?airportID=LNR",
    "Distance": 0
  },
  "KLSE": {
    "Id": "KLSE",
    "Name": "LA CROSSE RGNL",
    "Latitude": 43.879278,
    "Longitude": -91.256639,
    "Url": "https://www.airportiq5010.com/5010ReportRouter/default.aspx?airportID=LSE",
    "Distance": 0
  },
  "KLUM": {
    "Id": "KLUM",
    "Name": "MENOMONIE",
    "Latitude": 44.892333,
    "Longitude": -91.867806,
    "Url": "https://www.airportiq5010.com/5010ReportRouter/default.aspx?airportID=LUM",
    "Distance": 0
  },
  "KMDZ": {
    "Id": "KMDZ",
    "Name": "TAYLOR COUNTY",
    "Latitude": 45.101317,
    "Longitude": -90.300172,
    "Url": "https://www.airportiq5010.com/5010ReportRouter/default.aspx?airportID=MDZ",
    "Distance": 0
  },
  "KMFI": {
    "Id": "KMFI",
    "Name": "MARSHFIELD MUNI",
    "Latitude": 44.636878,
    "Longitude": -90.189325,
    "Url": "https://www.airportiq5010.com/5010ReportRouter/default.aspx?airportID=MFI",
    "Distance": 0
  },
  "KMKE": {
    "Id": "KMKE",
    "Name": "GENERAL MITCHELL",
    "Latitude": 42.946931,
    "Longitude": -87.897064,
    "Url": "https://www.airportiq5010.com/5010ReportRouter/default.aspx?airportID=MKE",
    "Distance": 0
  },
  "KMNM": {
    "Id": "KMNM",
    "Name": "MENOMINEE RGNL",
    "Latitude": 45.126686,
    "Longitude": -87.638542,
    "Url": "https://www.airportiq5010.com/5010ReportRouter/default.aspx?airportID=MNM",
    "Distance": 0
  },
  "KMRJ": {
    "Id": "KMRJ",
    "Name": "IOWA COUNTY",
    "Latitude": 42.886889,
    "Longitude": -90.236667,
    "Url": "https://www.airportiq5010.com/5010ReportRouter/default.aspx?airportID=MRJ",
    "Distance": 0
  },
  "KMSN": {
    "Id": "KMSN",
    "Name": "DANE COUNTY",
    "Latitude": 43.139878,
    "Longitude": -89.337503,
    "Url": "https://www.airportiq5010.com/5010ReportRouter/default.aspx?airportID=MSN",
    "Distance": 0
  },
  "KMTW": {
    "Id": "KMTW",
    "Name": "MANITOWOC COUNTY",
    "Latitude": 44.128778,
    "Longitude": -87.680583,
    "Url": "https://www.airportiq5010.com/5010ReportRouter/default.aspx?airportID=MTW",
    "Distance": 0
  },
  "KMWC": {
    "Id": "KMWC",
    "Name": "LAWRENCE J",
    "Latitude": 43.110389,
    "Longitude": -88.034417,
    "Url": "https://www.airportiq5010.com/5010ReportRouter/default.aspx?airportID=MWC",
    "Distance": 0
  },
  "KOCQ": {
    "Id": "KOCQ",
    "Name": "OCONTO-J DOUGLAS",
    "Latitude": 44.874056,
    "Longitude": -87.909769,
    "Url": "https://www.airportiq5010.com/5010ReportRouter/default.aspx?airportID=OCQ",
    "Distance": 0
  },
  "KOEO": {
    "Id": "KOEO",
    "Name": "L O SIMENSTAD MUNI",
    "Latitude": 45.309342,
    "Longitude": -92.690122,
    "Url": "https://www.airportiq5010.com/5010ReportRouter/default.aspx?airportID=OEO",
    "Distance": 0
  },
  "KOLG": {
    "Id": "KOLG",
    "Name": "SOLON SPRINGS MUNI",
    "Latitude": 46.31475,
    "Longitude": -91.816375,
    "Url": "https://www.airportiq5010.com/5010ReportRouter/default.aspx?airportID=OLG",
    "Distance": 0
  },
  "KOSH": {
    "Id": "KOSH",
    "Name": "WITTMAN RGNL",
    "Latitude": 43.984489,
    "Longitude": -88.556933,
    "Url": "https://www.airportiq5010.com/5010ReportRouter/default.aspx?airportID=OSH",
    "Distance": 0
  },
  "KOVS": {
    "Id": "KOVS",
    "Name": "BOSCOBEL",
    "Latitude": 43.16085,
    "Longitude": -90.673719,
    "Url": "https://www.airportiq5010.com/5010ReportRouter/default.aspx?airportID=OVS",
    "Distance": 0
  },
  "KPBH": {
    "Id": "KPBH",
    "Name": "PRICE COUNTY",
    "Latitude": 45.708833,
    "Longitude": -90.4025,
    "Url": "https://www.airportiq5010.com/5010ReportRouter/default.aspx?airportID=PBH",
    "Distance": 0
  },
  "KPCZ": {
    "Id": "KPCZ",
    "Name": "WAUPACA MUNI",
    "Latitude": 44.33325,
    "Longitude": -89.019778,
    "Url": "https://www.airportiq5010.com/5010ReportRouter/default.aspx?airportID=PCZ",
    "Distance": 0
  },
  "KPDC": {
    "Id": "KPDC",
    "Name": "PRAIRIE DU CHIEN",
    "Latitude": 43.019283,
    "Longitude": -91.123731,
    "Url": "https://www.airportiq5010.com/5010ReportRouter/default.aspx?airportID=PDC",
    "Distance": 0
  },
  "KPKF": {
    "Id": "KPKF",
    "Name": "PARK FALLS MUNI",
    "Latitude": 45.955089,
    "Longitude": -90.424433,
    "Url": "https://www.airportiq5010.com/5010ReportRouter/default.aspx?airportID=PKF",
    "Distance": 0
  },
  "KPVB": {
    "Id": "KPVB",
    "Name": "PLATTEVILLE MUNI",
    "Latitude": 42.689361,
    "Longitude": -90.444389,
    "Url": "https://www.airportiq5010.com/5010ReportRouter/default.aspx?airportID=PVB",
    "Distance": 0
  },
  "KRAC": {
    "Id": "KRAC",
    "Name": "BATTEN INTL",
    "Latitude": 42.761167,
    "Longitude": -87.813917,
    "Url": "https://www.airportiq5010.com/5010ReportRouter/default.aspx?airportID=RAC",
    "Distance": 0
  },
  "KRCX": {
    "Id": "KRCX",
    "Name": "RUSK COUNTY",
    "Latitude": 45.496583,
    "Longitude": -91.000186,
    "Url": "https://www.airportiq5010.com/5010ReportRouter/default.aspx?airportID=RCX",
    "Distance": 0
  },
  "KRGK": {
    "Id": "KRGK",
    "Name": "RED WING RGNL",
    "Latitude": 44.589361,
    "Longitude": -92.484972,
    "Url": "https://www.airportiq5010.com/5010ReportRouter/default.aspx?airportID=RGK",
    "Distance": 0
  },
  "KRHI": {
    "Id": "KRHI",
    "Name": "RHINELANDER-ONEIDA",
    "Latitude": 45.630897,
    "Longitude": -89.466628,
    "Url": "https://www.airportiq5010.com/5010ReportRouter/default.aspx?airportID=RHI",
    "Distance": 0
  },
  "KRNH": {
    "Id": "KRNH",
    "Name": "NEW RICHMOND RGNL",
    "Latitude": 45.147778,
    "Longitude": -92.539167,
    "Url": "https://www.airportiq5010.com/5010ReportRouter/default.aspx?airportID=RNH",
    "Distance": 0
  },
  "KRPD": {
    "Id": "KRPD",
    "Name": "RICE LAKE RGNL -",
    "Latitude": 45.420111,
    "Longitude": -91.773333,
    "Url": "https://www.airportiq5010.com/5010ReportRouter/default.aspx?airportID=RPD",
    "Distance": 0
  },
  "KRRL": {
    "Id": "KRRL",
    "Name": "MERRILL MUNI",
    "Latitude": 45.198917,
    "Longitude": -89.712861,
    "Url": "https://www.airportiq5010.com/5010ReportRouter/default.aspx?airportID=RRL",
    "Distance": 0
  },
  "KRYV": {
    "Id": "KRYV",
    "Name": "WATERTOWN MUNI",
    "Latitude": 43.169639,
    "Longitude": -88.723222,
    "Url": "https://www.airportiq5010.com/5010ReportRouter/default.aspx?airportID=RYV",
    "Distance": 0
  },
  "KRZN": {
    "Id": "KRZN",
    "Name": "BURNETT COUNTY",
    "Latitude": 45.823464,
    "Longitude": -92.373692,
    "Url": "https://www.airportiq5010.com/5010ReportRouter/default.aspx?airportID=RZN",
    "Distance": 0
  },
  "KSBM": {
    "Id": "KSBM",
    "Name": "SHEBOYGAN COUNTY",
    "Latitude": 43.769778,
    "Longitude": -87.851722,
    "Url": "https://www.airportiq5010.com/5010ReportRouter/default.aspx?airportID=SBM",
    "Distance": 0
  },
  "KSSQ": {
    "Id": "KSSQ",
    "Name": "SHELL LAKE MUNI",
    "Latitude": 45.731381,
    "Longitude": -91.920661,
    "Url": "https://www.airportiq5010.com/5010ReportRouter/default.aspx?airportID=SSQ",
    "Distance": 0
  },
  "KSTE": {
    "Id": "KSTE",
    "Name": "STEVENS POINT MUNI",
    "Latitude": 44.545133,
    "Longitude": -89.530283,
    "Url": "https://www.airportiq5010.com/5010ReportRouter/default.aspx?airportID=STE",
    "Distance": 0
  },
  "KSUE": {
    "Id": "KSUE",
    "Name": "DOOR COUNTY",
    "Latitude": 44.843667,
    "Longitude": -87.421528,
    "Url": "https://www.airportiq5010.com/5010ReportRouter/default.aspx?airportID=SUE",
    "Distance": 0
  },
  "KSUW": {
    "Id": "KSUW",
    "Name": "RICHARD I BONG",
    "Latitude": 46.689683,
    "Longitude": -92.094642,
    "Url": "https://www.airportiq5010.com/5010ReportRouter/default.aspx?airportID=SUW",
    "Distance": 0
  },
  "KTKV": {
    "Id": "KTKV",
    "Name": "TOMAHAWK RGNL",
    "Latitude": 45.469361,
    "Longitude": -89.804889,
    "Url": "https://www.airportiq5010.com/5010ReportRouter/default.aspx?airportID=TKV",
    "Distance": 0
  },
  "KUBE": {
    "Id": "KUBE",
    "Name": "CUMBERLAND MUNI",
    "Latitude": 45.506097,
    "Longitude": -91.9808,
    "Url": "https://www.airportiq5010.com/5010ReportRouter/default.aspx?airportID=UBE",
    "Distance": 0
  },
  "KUES": {
    "Id": "KUES",
    "Name": "WAUKESHA COUNTY",
    "Latitude": 43.041028,
    "Longitude": -88.237056,
    "Url": "https://www.airportiq5010.com/5010ReportRouter/default.aspx?airportID=UES",
    "Distance": 0
  },
  "KUNU": {
    "Id": "KUNU",
    "Name": "DODGE COUNTY",
    "Latitude": 43.426472,
    "Longitude": -88.703861,
    "Url": "https://www.airportiq5010.com/5010ReportRouter/default.aspx?airportID=UNU",
    "Distance": 0
  },
  "KVIQ": {
    "Id": "KVIQ",
    "Name": "NEILLSVILLE MUNI",
    "Latitude": 44.558111,
    "Longitude": -90.51225,
    "Url": "https://www.airportiq5010.com/5010ReportRouter/default.aspx?airportID=VIQ",
    "Distance": 0
  },
  "KW19": {
    "Id": "KW19",
    "Name": "VERONA",
    "Latitude": 42.989467,
    "Longitude": -89.509478,
    "Url": "https://www.airportiq5010.com/5010ReportRouter/default.aspx?airportID=W19",
    "Distance": 0
  },
  "KW23": {
    "Id": "KW23",
    "Name": "WILD ROSE IDLEWILD",
    "Latitude": 44.197753,
    "Longitude": -89.217894,
    "Url": "https://www.airportiq5010.com/5010ReportRouter/default.aspx?airportID=W23",
    "Distance": 0
  },
  "KW34": {
    "Id": "KW34",
    "Name": "SHIOCTON",
    "Latitude": 44.455461,
    "Longitude": -88.561806,
    "Url": "https://www.airportiq5010.com/5010ReportRouter/default.aspx?airportID=W34",
    "Distance": 0
  },
  "KY23": {
    "Id": "KY23",
    "Name": "CHETEK",
    "Latitude": 45.306486,
    "Longitude": -91.636822,
    "Url": "https://www.airportiq5010.com/5010ReportRouter/default.aspx?airportID=Y23",
    "Distance": 0
  },
  "KY50": {
    "Id": "KY50",
    "Name": "WAUTOMA MUNI",
    "Latitude": 44.043133,
    "Longitude": -89.305689,
    "Url": "https://www.airportiq5010.com/5010ReportRouter/default.aspx?airportID=Y50",
    "Distance": 0
  },
  "KY51": {
    "Id": "KY51",
    "Name": "VIROQUA MUNI",
    "Latitude": 43.579639,
    "Longitude": -90.897722,
    "Url": "https://www.airportiq5010.com/5010ReportRouter/default.aspx?airportID=Y51",
    "Distance": 0
  },
  "KY55": {
    "Id": "KY55",
    "Name": "CRANDON/STEVE",
    "Latitude": 45.522647,
    "Longitude": -88.928436,
    "Url": "https://www.airportiq5010.com/5010ReportRouter/default.aspx?airportID=Y55",
    "Distance": 0
  },
  "KY72": {
    "Id": "KY72",
    "Name": "BLOYER FIELD",
    "Latitude": 43.976222,
    "Longitude": -90.480611,
    "Url": "https://www.airportiq5010.com/5010ReportRouter/default.aspx?airportID=Y72",
    "Distance": 0
  },
  "KY77": {
    "Id": "KY77",
    "Name": "BAYFIELD COUNTY",
    "Latitude": 46.576328,
    "Longitude": -91.458522,
    "Url": "https://www.airportiq5010.com/5010ReportRouter/default.aspx?airportID=Y77",
    "Distance": 0
  }
}